mat_wrap/__init__.py
mat_wrap/mat_wrap.py
mat_wrap-0.0.8.dist-info/METADATA
mat_wrap-0.0.8.dist-info/WHEEL
mat_wrap-0.0.8.dist-info/top_level.txt
mat_wrap-0.0.8.dist-info/RECORD
