Metadata-Version: 2.1
Name: mat-wrap
Version: 0.0.8
Summary: This is a simple and easy wrapper for matlab and python3
Home-page: https://github.com/sbeer3/mat_wrapper
Author: Simon Beer
Author-email: sbeer3@uwyo.edu
License: UNKNOWN
Project-URL: Bug Tracker, https://github.com/sbeer3/mat_wrapper/issues
Platform: UNKNOWN
Classifier: Programming Language :: Python :: 3
Classifier: License :: OSI Approved :: GNU General Public License v3 or later (GPLv3+)
Classifier: Operating System :: OS Independent
Requires-Python: >=3.6
